addfips/__init__.py
addfips/__main__.py
addfips/addfips.py
addfips/data/counties_2000.csv
addfips/data/counties_2010.csv
addfips/data/counties_2015.csv
addfips/data/counties_2020.csv
addfips/data/states.csv
addfips-0.4.2.dist-info/LICENSE
addfips-0.4.2.dist-info/METADATA
addfips-0.4.2.dist-info/WHEEL
addfips-0.4.2.dist-info/entry_points.txt
addfips-0.4.2.dist-info/top_level.txt
addfips-0.4.2.dist-info/zip-safe
addfips-0.4.2.dist-info/RECORD
