Metadata-Version: 2.1
Name: addfips
Version: 0.4.2
Summary: Add county FIPS to tabular data
Author-email: Neil Freeman <contact@fakeisthenewreal.org>
License: GNU GENERAL PUBLIC LICENSE Version 3, 29 June 2007
Project-URL: Homepage, http://github.com/fitnr/addfips
Keywords: usa,data,federal information processing standard
Classifier: Intended Audience :: Developers
Classifier: Programming Language :: Python :: 3.7
Classifier: Programming Language :: Python :: 3.8
Classifier: Programming Language :: Python :: 3.9
Classifier: Programming Language :: Python :: 3.10
Classifier: Programming Language :: Python :: 3.11
Classifier: Operating System :: OS Independent
Classifier: Natural Language :: English
Classifier: License :: OSI Approved :: GNU General Public License v3 (GPLv3)
Requires-Python: >=3.7
License-File: LICENSE
Requires-Dist: importlib_resources; python_version < "3.9"
Provides-Extra: tests
Requires-Dist: coverage[toml]>=6; extra == "tests"
